keycloak/__init__.py
keycloak/config.py
keycloak/constants.py
keycloak/log.py
keycloak/utils.py
keycloak/welcome.py
keycloak/core/__init__.py
keycloak/core/authentication.py
keycloak/core/authorization.py
keycloak/core/resource.py
keycloak/core/token.py
keycloak/core/asynchronous/__init__.py
keycloak/core/asynchronous/authentication.py
keycloak/core/asynchronous/authorization.py
keycloak/core/asynchronous/resource.py
keycloak/core/asynchronous/token.py
keycloak/extensions/__init__.py
keycloak/extensions/django.py
keycloak/extensions/flask.py
keycloak/extensions/starlette.py
ndd_forked_keycloak-3.1.2.dist-info/METADATA
ndd_forked_keycloak-3.1.2.dist-info/WHEEL
ndd_forked_keycloak-3.1.2.dist-info/entry_points.txt
ndd_forked_keycloak-3.1.2.dist-info/top_level.txt
ndd_forked_keycloak-3.1.2.dist-info/RECORD
