Metadata-Version: 2.1
Name: ndd-forked-keycloak
Version: 3.1.2
Summary: Forked from https://github.com/keycloak-client/keycloak-client
Home-page: https://github.com/hpduongducnhan/keycloak-client
Author: hpduongducnhan
Author-email: hpduongducnhan@gmail.com
Maintainer: hpduongducnhan
Maintainer-email: hpduongducnhan@gmail.com
License: MIT
Download-URL: https://github.com/hpduongducnhan/keycloak-client/tarball/master
Platform: UNKNOWN
Classifier: Development Status :: 4 - Beta
Classifier: License :: OSI Approved :: MIT License
Classifier: Topic :: Software Development :: Libraries :: Python Modules
Classifier: Intended Audience :: Developers
Classifier: Programming Language :: Python :: 3
Requires-Python: <4,>=3.0.*
Requires-Dist: Django
Requires-Dist: Flask
Requires-Dist: starlette
Requires-Dist: httpx
Requires-Dist: requests
Requires-Dist: python-jose
Requires-Dist: pytest
